streamlit_chatbox/__init__.py
streamlit_chatbox/elements.py
streamlit_chatbox/flows.py
streamlit_chatbox/messages.py
streamlit_chatbox/thirdpart.py
streamlit_chatbox/inputs/__init__.py
streamlit_chatbox/inputs/example.py
streamlit_chatbox-1.1.13.dist-info/METADATA
streamlit_chatbox-1.1.13.dist-info/WHEEL
streamlit_chatbox-1.1.13.dist-info/top_level.txt
streamlit_chatbox-1.1.13.dist-info/RECORD
