Metadata-Version: 2.1
Name: streamlit-chatbox
Version: 1.1.13
Summary: A chat box and some helpful tools used to build chatbot app with streamlit
Home-page: https://github.com/liunux4odoo/streamlit-chatbox
Author: liunux
Author-email: liunux@qq.com
Requires-Python: >=3.8
Requires-Dist: streamlit >=1.26.0
Requires-Dist: simplejson
Requires-Dist: streamlit-feedback
Requires-Dist: streamlit-markdown >=1.0.9
